nanasqlite/__init__.py
nanasqlite/async_core.py
nanasqlite/cache.py
nanasqlite/core.py
nanasqlite/exceptions.py
nanasqlite/py.typed
nanasqlite/sql_utils.py
nanasqlite/utils.py
nanasqlite-1.3.1.dist-info/licenses/LICENSE
nanasqlite-1.3.1.dist-info/METADATA
nanasqlite-1.3.1.dist-info/WHEEL
nanasqlite-1.3.1.dist-info/top_level.txt
nanasqlite-1.3.1.dist-info/RECORD
