Metadata-Version: 2.4
Name: nanasqlite
Version: 1.3.1
Summary: A dict-like SQLite wrapper with APSW for instant persistence and memory caching
Author-email: Disnana <support@disnana.com>
License-Expression: MIT
Project-URL: Homepage, https://github.com/disnana/nanasqlite
Project-URL: Documentation, https://nanasqlite.disnana.com/
Project-URL: Repository, https://github.com/disnana/nanasqlite
Project-URL: Issues, https://github.com/disnana/nanasqlite/issues
Keywords: sqlite,apsw,dict,database,persistence,cache,key-value,nosql
Classifier: Development Status :: 5 - Production/Stable
Classifier: Intended Audience :: Developers
Classifier: Operating System :: OS Independent
Classifier: Programming Language :: Python :: 3
Classifier: Programming Language :: Python :: 3.9
Classifier: Programming Language :: Python :: 3.10
Classifier: Programming Language :: Python :: 3.11
Classifier: Programming Language :: Python :: 3.12
Classifier: Programming Language :: Python :: 3.13
Classifier: Programming Language :: Python :: 3.14
Classifier: Topic :: Database
Classifier: Topic :: Software Development :: Libraries :: Python Modules
Classifier: Typing :: Typed
Requires-Python: >=3.9
License-File: LICENSE
Requires-Dist: apsw>=3.40.0.0
Provides-Extra: speed
Requires-Dist: lru-dict>=1.3.0; extra == "speed"
Provides-Extra: encryption
Requires-Dist: cryptography>=42.0.0; extra == "encryption"
Provides-Extra: dev
Requires-Dist: pytest>=7.0.0; extra == "dev"
Requires-Dist: pytest-cov>=4.0.0; extra == "dev"
Requires-Dist: pytest-asyncio<2.0.0,>=0.21.0; extra == "dev"
Requires-Dist: pydantic>=2.0.0; extra == "dev"
Requires-Dist: tox>=4.0.0; extra == "dev"
Requires-Dist: ruff>=0.8.0; extra == "dev"
Requires-Dist: mypy>=1.13.0; extra == "dev"
Requires-Dist: pytest-xdist>=3.0.0; extra == "dev"
Requires-Dist: pytest-benchmark>=4.0.0; extra == "dev"
Dynamic: license-file
